kurobako/__init__.py
kurobako/problem.py
kurobako/solver/__init__.py
kurobako/solver/optuna.py
kurobako-0.2.1.dist-info/LICENSE
kurobako-0.2.1.dist-info/METADATA
kurobako-0.2.1.dist-info/WHEEL
kurobako-0.2.1.dist-info/top_level.txt
kurobako-0.2.1.dist-info/RECORD
