Metadata-Version: 2.1
Name: kurobako
Version: 0.2.1
Summary: A Python library to help implementing kurobako's solvers and problems
Home-page: https://github.com/sile/kurobako-py
Author: Takeru Ohta
Author-email: phjgt308@gmail.com
License: MIT
Platform: UNKNOWN
Requires-Dist: numpy
Provides-Extra: checking
Requires-Dist: black ; extra == 'checking'
Requires-Dist: hacking ; extra == 'checking'
Requires-Dist: mypy ; extra == 'checking'
